baseq/__init__.py
baseq/cmd.py
baseq/setting.py
baseq/align/__init__.py
baseq/align/blast.py
baseq/align/bowtie2.py
baseq/align/bwa.py
baseq/align/cmd.py
baseq/align/hisat2.py
baseq/align/star.py
baseq/bam/__init__.py
baseq/bam/bamtype.py
baseq/bam/cigar.py
baseq/bam/cmd.py
baseq/bam/doc.py
baseq/bam/stats.py
baseq/bam/depth/__init__.py
baseq/bam/depth/depth.py
baseq/bam/depth/plot.py
baseq/bam/qc/__init__.py
baseq/bam/qc/complexity.py
baseq/bam/qc/duplicate.py
baseq/cnv/plots/__init__.py
baseq/cnv/plots/genome.py
baseq/cnv/plots/heatmap.py
baseq/cnv/plots/region.py
baseq/drops/__init__.py
baseq/drops/aggregate.py
baseq/drops/bam_parser.py
baseq/drops/cmd.py
baseq/drops/exp_stats.py
baseq/drops/run_star.py
baseq/drops/tag_gene.py
baseq/drops/apa/UTR.py
baseq/drops/apa/__init__.py
baseq/drops/apa/cmd.py
baseq/drops/apa/docs.py
baseq/drops/apa/genes.py
baseq/drops/apa/samples.py
baseq/drops/apa/scaner.py
baseq/drops/barcode/__init__.py
baseq/drops/barcode/count.py
baseq/drops/barcode/extract.py
baseq/drops/barcode/split.py
baseq/drops/barcode/split_fast.py
baseq/drops/barcode/stats.py
baseq/drops/barcode/whitelist.py
baseq/drops/cellranger/__init__.py
baseq/drops/cellranger/cluster.py
baseq/drops/cellranger/cmd.py
baseq/drops/cellranger/docs.py
baseq/fastq/__init__.py
baseq/fastq/barcode.py
baseq/fastq/cmd.py
baseq/fastq/docs.py
baseq/fastq/files.py
baseq/fastq/filter.py
baseq/fastq/quality.py
baseq/mgt/__init__.py
baseq/mgt/check.py
baseq/mgt/command.py
baseq/mgt/config.py
baseq/mgt/history.py
baseq/rna/__init__.py
baseq/rna/aligner.py
baseq/rna/build_table.py
baseq/rna/cmd.py
baseq/rna/docs.py
baseq/rna/pipeline.py
baseq/rna/quantify.py
baseq/rna/quantity_align.py
baseq/rna/salmon.py
baseq/rna/star.py
baseq/rna/qc/__init__.py
baseq/rna/qc/corrheatmap.py
baseq/rna/qc/exp_table.py
baseq/rna/qc/markers.py
baseq/rna/qc/pca.py
baseq/rna/qc/precision.py
baseq/rna/qc/scatterplot.py
baseq_drops-0.3.5.dist-info/DESCRIPTION.rst
baseq_drops-0.3.5.dist-info/METADATA
baseq_drops-0.3.5.dist-info/RECORD
baseq_drops-0.3.5.dist-info/WHEEL
baseq_drops-0.3.5.dist-info/entry_points.txt
baseq_drops-0.3.5.dist-info/metadata.json
baseq_drops-0.3.5.dist-info/top_level.txt
