Metadata-Version: 2.0
Name: baseq-drops
Version: 0.3.5
Summary: Pipeline for processing Drop-seq/10X/inDrop datas
Home-page: https://gene.pku.edu.cn
Author: Xiannian Zhang
Author-email: friedpine@gmail.com
License: UNKNOWN
Keywords: sample setuptools development
Platform: UNKNOWN
Classifier: Development Status :: 3 - Alpha
Classifier: Intended Audience :: Developers
Classifier: Topic :: Software Development :: Build Tools
Classifier: License :: OSI Approved :: MIT License
Classifier: Programming Language :: Python :: 3.6
Requires-Dist: click
Requires-Dist: configparser
Requires-Dist: jinja2
Requires-Dist: matplotlib
Requires-Dist: numpy
Requires-Dist: pandas
Provides-Extra: dev
Requires-Dist: check-manifest; extra == 'dev'
Provides-Extra: test
Requires-Dist: coverage; extra == 'test'
